LICENSE
MANIFEST.in
README.md
pyproject.toml
setup.cfg
setup.py
environment/__init__.py
environment/admin.py
environment/api_types.py
environment/apps.py
environment/constants.py
environment/decorators.py
environment/deserializers.py
environment/entities.py
environment/exceptions.py
environment/forms.py
environment/mailers.py
environment/models.py
environment/react_views.py
environment/serializers.py
environment/services.py
environment/signals.py
environment/tasks.py
environment/urls.py
environment/utilities.py
environment/validators.py
environment/views.py
environment/api/__init__.py
environment/api/decorators.py
environment/migrations/00012_bucketsharinginvite.py
environment/migrations/0001_initial.py
environment/migrations/0002_billingsetup.py
environment/migrations/0003_cloudidentity_is_workspace_done.py
environment/migrations/0004_auto_20220309_0330.py
environment/migrations/0005_workflow.py
environment/migrations/0006_delete_billingsetup.py
environment/migrations/0007_billingaccountsharinginvite.py
environment/migrations/0008_workflow_workspace_name.py
environment/migrations/0009_billingaccountsharinginvite_is_revoked.py
environment/migrations/0010_alter_workflow_project_alter_workflow_type_and_more.py
environment/migrations/0011_refactor_workflow.py
environment/migrations/0013_bucketsharinginvite_type_and_more.py
environment/migrations/0014_googlegroup_cloudidentity_user_groups.py
environment/migrations/0015_gcpregion_instancetype_vminstance.py
environment/migrations/0016_remove_vminstance_gpu_attachable_gpuaccelerator_and_more.py
environment/migrations/0017_gpuaccelerator_display_name.py
environment/migrations/__init__.py
environment/static/environment/.DS_Store
environment/static/environment/css/bucket_files_dropzone.css
environment/static/environment/css/collaborator_management.css
environment/static/environment/css/creation_form.css
environment/static/environment/css/datasets_monitoring_data.css
environment/static/environment/css/environment-base.css
hdn_research_environment.egg-info/PKG-INFO
hdn_research_environment.egg-info/SOURCES.txt
hdn_research_environment.egg-info/dependency_links.txt
hdn_research_environment.egg-info/requires.txt
hdn_research_environment.egg-info/top_level.txt