Metadata-Version: 2.2
Name: hdn-research-environment
Version: 3.2.17
Summary: A Django app for supporting cloud-native research environments
Home-page: https://www.healthdatanexus.ai/
Author: Your Name
Author-email: yourname@example.com
License: BSD-3-Clause  # Example license
Classifier: Environment :: Web Environment
Classifier: Framework :: Django
Classifier: Framework :: Django :: 2.2
Classifier: Intended Audience :: Developers
Classifier: License :: OSI Approved :: BSD License
Classifier: Operating System :: OS Independent
Classifier: Programming Language :: Python
Classifier: Programming Language :: Python :: 3
Classifier: Programming Language :: Python :: 3 :: Only
Classifier: Programming Language :: Python :: 3.7
Classifier: Programming Language :: Python :: 3.8
Classifier: Programming Language :: Python :: 3.9
Classifier: Topic :: Internet :: WWW/HTTP
Classifier: Topic :: Internet :: WWW/HTTP :: Dynamic Content
Requires-Python: >=3.7
License-File: LICENSE
Requires-Dist: Django>=4.2.18
Requires-Dist: google-cloud-workflows>=1.6.1
Requires-Dist: django-background-tasks-updated>=1.2.7
Requires-Dist: djangorestframework>=3.15.2
